gwr_inversion.py
gwr_inversion-1.0.1.dist-info/LICENSE
gwr_inversion-1.0.1.dist-info/METADATA
gwr_inversion-1.0.1.dist-info/WHEEL
gwr_inversion-1.0.1.dist-info/top_level.txt
gwr_inversion-1.0.1.dist-info/RECORD
