Metadata-Version: 2.1
Name: gwr-inversion
Version: 1.0.1
Summary: GWR Algorithm Numerical Laplace Inversion
Home-page: https://github.com/petbox-dev/gwr
Author: David S. Fulford
Author-email: petbox.dev@gmail.com
License: UNKNOWN
Keywords: laplace,inversion,transform,gwr
Platform: UNKNOWN
Classifier: Development Status :: 5 - Production/Stable
Classifier: Intended Audience :: Science/Research
Classifier: Intended Audience :: Education
Classifier: Intended Audience :: Developers
Classifier: Natural Language :: English
Classifier: License :: OSI Approved :: MIT License
Classifier: Programming Language :: Python :: 3.7
Classifier: Programming Language :: Python :: 3.8
Classifier: Programming Language :: Python :: Implementation :: CPython
Classifier: Topic :: Scientific/Engineering
Classifier: Topic :: Scientific/Engineering :: Mathematics
Classifier: Topic :: Software Development :: Libraries
Classifier: Typing :: Typed
Requires-Python: >=3.7
Requires-Dist: numpy (>=1.17)
Requires-Dist: mpmath (>=1.1.0)
